medivisio.py
medivisio-0.0.4.dist-info/METADATA
medivisio-0.0.4.dist-info/WHEEL
medivisio-0.0.4.dist-info/top_level.txt
medivisio-0.0.4.dist-info/RECORD
