Metadata-Version: 2.1
Name: medivisio
Version: 0.0.4
Summary: This script helps to visualise 3D medical images of type DICOM and NII
Author: Dr. Shakeel Ahmad Sheikh
Classifier: Programming Language :: Python :: 3.11
Requires-Dist: numpy
Requires-Dist: pydicom
Requires-Dist: matplotlib
Requires-Dist: nibabel
